uwacan/__init__.py
uwacan/_core.py
uwacan/_filterbank.py
uwacan/_version.py
uwacan/analysis.py
uwacan/background.py
uwacan/positional.py
uwacan/propagation.py
uwacan/recordings.py
uwacan/source_models.py
uwacan-2.2.1.dist-info/METADATA
uwacan-2.2.1.dist-info/WHEEL
uwacan-2.2.1.dist-info/licenses/LICENSE
uwacan-2.2.1.dist-info/RECORD
