Metadata-Version: 2.4
Name: uwacan
Version: 2.2.1
Summary: Underwater Acoustic Analysis tools
Project-URL: Repository, https://github.com/CarlAndersson/underwater-acoustics-analysis
Author-email: Carl Andersson <carl.andersson@ivl.se>
License-File: LICENSE
Requires-Python: >=3.11
Requires-Dist: gpxpy
Requires-Dist: numba>=0.60
Requires-Dist: numpy
Requires-Dist: pandas
Requires-Dist: plotly
Requires-Dist: scipy
Requires-Dist: sounddevice
Requires-Dist: soundfile
Requires-Dist: whenever<0.7,>=0.6.5
Requires-Dist: xarray
Requires-Dist: zarr<3,>=2.18
Provides-Extra: cli
Requires-Dist: dash>=3.0.4; extra == 'cli'
